odoo8_addon_product_m2mcategories-8.0.1.0.3-nspkg.pth
odoo_addons/product_m2mcategories/__init__.py
odoo_addons/product_m2mcategories/__openerp__.py
odoo_addons/product_m2mcategories/i18n/ca.po
odoo_addons/product_m2mcategories/i18n/de.po
odoo_addons/product_m2mcategories/i18n/es.po
odoo_addons/product_m2mcategories/i18n/fr.po
odoo_addons/product_m2mcategories/i18n/fr_BE.po
odoo_addons/product_m2mcategories/i18n/product_m2mcategories.pot
odoo_addons/product_m2mcategories/i18n/sl.po
odoo_addons/product_m2mcategories/i18n/sv.po
odoo_addons/product_m2mcategories/i18n/tr.po
odoo_addons/product_m2mcategories/models/__init__.py
odoo_addons/product_m2mcategories/models/product.py
odoo_addons/product_m2mcategories/static/description/icon.png
odoo_addons/product_m2mcategories/views/product_view.xml
odoo8_addon_product_m2mcategories-8.0.1.0.3.dist-info/METADATA
odoo8_addon_product_m2mcategories-8.0.1.0.3.dist-info/WHEEL
odoo8_addon_product_m2mcategories-8.0.1.0.3.dist-info/namespace_packages.txt
odoo8_addon_product_m2mcategories-8.0.1.0.3.dist-info/top_level.txt
odoo8_addon_product_m2mcategories-8.0.1.0.3.dist-info/RECORD
