Metadata-Version: 2.1
Name: odoo8-addon-product-m2mcategories
Version: 8.0.1.0.3
Summary: Product - Many Categories
Home-page: https://odoo-community.org/
Author: Sharoon Thomas,Odoo Community Association (OCA)
Author-email: support@odoo-community.org
License: GPL-3 or any later version
Platform: UNKNOWN
Classifier: Programming Language :: Python
Classifier: Framework :: Odoo
Classifier: License :: OSI Approved :: GNU General Public License v3 or later (GPLv3+)
Requires-Python: ~=2.7
Requires-Dist: odoo (<9.0a,>=8.0a)
